react_native_godot_mcp.py
iflow_mcp_vredrick_react_native_godot_mcp-1.0.0.dist-info/METADATA
iflow_mcp_vredrick_react_native_godot_mcp-1.0.0.dist-info/WHEEL
iflow_mcp_vredrick_react_native_godot_mcp-1.0.0.dist-info/entry_points.txt
iflow_mcp_vredrick_react_native_godot_mcp-1.0.0.dist-info/RECORD
