Metadata-Version: 2.4
Name: iflow-mcp_vredrick_react-native-godot-mcp
Version: 1.0.0
Summary: MCP server for React Native Godot documentation fetching and searching
Requires-Python: >=3.8
Requires-Dist: fastmcp>=0.1.0
Requires-Dist: httpx>=0.24.0
Requires-Dist: mcp>=1.0.0
Requires-Dist: pydantic>=2.0.0
